UniqueIDV/__init__.py
UniqueIDV-2.dist-info/METADATA
UniqueIDV-2.dist-info/WHEEL
UniqueIDV-2.dist-info/top_level.txt
UniqueIDV-2.dist-info/RECORD
