Metadata-Version: 2.1
Name: UniqueIDV
Version: 2
Summary: create id in scripts
Author: Damian Payano
Author-email: damiangamesss464@gmail.com
Requires-Python: >=3.7
